.gitignore
CHANGES.rst
MANIFEST.in
README.rst
setup.py
src/collective/__init__.py
src/collective.panels.egg-info/PKG-INFO
src/collective.panels.egg-info/SOURCES.txt
src/collective.panels.egg-info/dependency_links.txt
src/collective.panels.egg-info/entry_points.txt
src/collective.panels.egg-info/namespace_packages.txt
src/collective.panels.egg-info/not-zip-safe
src/collective.panels.egg-info/requires.txt
src/collective.panels.egg-info/top_level.txt
src/collective/panels/__init__.py
src/collective/panels/browser.py
src/collective/panels/configure.zcml
src/collective/panels/content.py
src/collective/panels/controlpanel.py
src/collective/panels/grid.py
src/collective/panels/i18n.py
src/collective/panels/interfaces.py
src/collective/panels/meta.zcml
src/collective/panels/profiles.zcml
src/collective/panels/rebuild_i18n.sh
src/collective/panels/traversal.py
src/collective/panels/upgrades.py
src/collective/panels/vocabularies.py
src/collective/panels/zcml.py
src/collective/panels/layouts/horizontal.pt
src/collective/panels/layouts/left.pt
src/collective/panels/layouts/onethirdleft.pt
src/collective/panels/layouts/onethirdright.pt
src/collective/panels/layouts/right.pt
src/collective/panels/layouts/splithalf.pt
src/collective/panels/layouts/splitonethird.pt
src/collective/panels/layouts/splittwothirds.pt
src/collective/panels/layouts/vertical.pt
src/collective/panels/locales/collective.panels.pot
src/collective/panels/locales/da/LC_MESSAGES/collective.panels.mo
src/collective/panels/locales/da/LC_MESSAGES/collective.panels.po
src/collective/panels/locales/nl/LC_MESSAGES/collective.panels.mo
src/collective/panels/locales/nl/LC_MESSAGES/collective.panels.po
src/collective/panels/profile/browserlayer.xml
src/collective/panels/profile/controlpanel.xml
src/collective/panels/profile/cssregistry.xml
src/collective/panels/profile/metadata.xml
src/collective/panels/profile/registry.xml
src/collective/panels/resources/panels-grid-classic-theme.css
src/collective/panels/resources/styles.css
src/collective/panels/templates/adding.pt
src/collective/panels/templates/display.pt
src/collective/panels/templates/link.pt
src/collective/panels/templates/manager.pt
src/collective/panels/templates/parent-link.pt
src/collective/panels/templates/portlet.pt