Metadata-Version: 1.1
Name: collective.panels
Version: 1.8
Summary: Add-on for Plone that adds portlet panels.
Home-page: UNKNOWN
Author: Malthe Borch
Author-email: mborch@gmail.com
License: GPLv2+
Keywords: plone portlets
Platform: UNKNOWN
Classifier: Framework :: Plone
Classifier: Framework :: Zope2
Classifier: Programming Language :: Python
